<annotation><folder>JPEGImages</folder><filename>1f58d85e-63c2-43b8-86f4-0a0f2e813579.jpg</filename><size><width>1136</width><height>640</height><depth>3</depth></size><object><name>wheat_flour_blue_label</name><pose>Unspecified</pose><truncated>0</truncated><difficult>0</difficult><bndbox><xmin>337</xmin><ymin>200</ymin><xmax>469</xmax><ymax>281</ymax></bndbox></object><object><name>wheat_flour_blue_label</name><pose>Unspecified</pose><truncated>0</truncated><difficult>0</difficult><bndbox><xmin>647</xmin><ymin>179</ymin><xmax>871</xmax><ymax>419</ymax></bndbox></object></annotation>